DiscoveryDV/__init__.py
DiscoveryDV/main.py
DiscoveryDV-0.5.dist-info/LICENSE.md
DiscoveryDV-0.5.dist-info/METADATA
DiscoveryDV-0.5.dist-info/WHEEL
DiscoveryDV-0.5.dist-info/top_level.txt
DiscoveryDV-0.5.dist-info/RECORD
