Metadata-Version: 2.1
Name: DiscoveryDV
Version: 0.5
Summary: Python package for interfacing with DiscoveryDV using its API
Home-page: https://www.decisionvis.com/ddv/
Author: DecisionVis LLC
Author-email: team@decisionvis.com
License: UNKNOWN
Platform: UNKNOWN
Classifier: Programming Language :: Python :: 3
Classifier: License :: OSI Approved :: MIT License
Classifier: Operating System :: OS Independent
Requires-Python: >=3.6
Requires-Dist: pyzmq
Requires-Dist: msgpack-python
